farstail/__init__.py
farstail/datasets/__init__.py
farstail/datasets/farstail.py
farstail/preprocessing/__init__.py
farstail/preprocessing/k_sequence.py
farstail/preprocessing/sequence.py
farstail/utils/__init__.py
farstail/utils/data_utils.py
farstail/utils/generic_utils.py
farstail-1.0.5.dist-info/LICENSE
farstail-1.0.5.dist-info/METADATA
farstail-1.0.5.dist-info/WHEEL
farstail-1.0.5.dist-info/top_level.txt
farstail-1.0.5.dist-info/RECORD
