Metadata-Version: 2.1
Name: farstail
Version: 1.0.5
Summary: Persian Natural Language Inference DataSet
Home-page: https://github.com/dml-qom/FarsTail
Author: FarsTail Team
Author-email: azari.jafari.m@gmail.com
License: UNKNOWN
Platform: UNKNOWN
Classifier: Programming Language :: Python :: 3
Classifier: License :: OSI Approved :: MIT License
Classifier: Operating System :: OS Independent
Classifier: Natural Language :: Persian
Requires-Python: >=3.6
